geomancer/__init__.py
geomancer/backend/__init__.py
geomancer/backend/settings.py
geomancer/backend/cores/__init__.py
geomancer/backend/cores/base.py
geomancer/backend/cores/bq.py
geomancer/backend/cores/sqlite.py
geomancer/spellbook/__init__.py
geomancer/spellbook/spellbook.py
geomancer/spells/__init__.py
geomancer/spells/base.py
geomancer/spells/distance_to_nearest.py
geomancer/spells/length_of.py
geomancer/spells/number_of.py
tests/backend/__init__.py
tests/backend/cores/__init__.py
tests/backend/cores/base_test_dbcore.py
tests/backend/cores/test_bq.py
tests/backend/cores/test_sqlite.py
geomancer-1.0.0.dist-info/LICENSE
geomancer-1.0.0.dist-info/METADATA
geomancer-1.0.0.dist-info/WHEEL
geomancer-1.0.0.dist-info/dependency_links.txt
geomancer-1.0.0.dist-info/top_level.txt
geomancer-1.0.0.dist-info/RECORD
