Metadata-Version: 2.1
Name: geomancer
Version: 1.0.0
Summary: Automated Geospatial Feature Engineering Library
Home-page: https://github.com/thinkingmachines/geomancer
Author: Thinking Machines Data Science
Author-email: hello@thinkingmachin.es
License: MIT license
Keywords: osm,python client,geospatial,bigquery,machine learning,feature engineering
Platform: UNKNOWN
Classifier: Development Status :: 5 - Production/Stable
Classifier: Intended Audience :: Developers
Classifier: Intended Audience :: Education
Classifier: Intended Audience :: Science/Research
Classifier: License :: OSI Approved :: MIT License
Classifier: Natural Language :: English
Classifier: Topic :: Scientific/Engineering
Classifier: Topic :: Scientific/Engineering :: GIS
Classifier: Topic :: Scientific/Engineering :: Artificial Intelligence
Classifier: Topic :: Software Development :: Libraries :: Python Modules
Classifier: Programming Language :: Python :: 3.6
Classifier: Programming Language :: Python :: 3.5
Requires-Dist: numpy
Requires-Dist: pandas
Requires-Dist: loguru
Requires-Dist: sqlalchemy
Requires-Dist: geoalchemy2
Requires-Dist: pytz
Requires-Dist: google-cloud-bigquery[pandas,pyarrow]
Requires-Dist: pybigquery
Provides-Extra: bq
Requires-Dist: google-cloud-bigquery[pandas,pyarrow] ; extra == 'bq'
Requires-Dist: pybigquery ; extra == 'bq'
Provides-Extra: psql
Provides-Extra: sqlite
